TaichiGAME/__init__.py
TaichiGAME/__main__.py
TaichiGAME/frame.py
TaichiGAME/main.py
TaichiGAME/scene.py
TaichiGAME/ti_scene.py
TaichiGAME/collision/__init__.py
TaichiGAME/collision/detector.py
TaichiGAME/collision/algorithm/__init__.py
TaichiGAME/collision/algorithm/clip.py
TaichiGAME/collision/algorithm/gjk.py
TaichiGAME/collision/algorithm/mpr.py
TaichiGAME/collision/algorithm/sat.py
TaichiGAME/collision/broad_phase/__init__.py
TaichiGAME/collision/broad_phase/aabb.py
TaichiGAME/collision/broad_phase/dbvh.py
TaichiGAME/collision/broad_phase/dbvt.py
TaichiGAME/collision/broad_phase/grid.py
TaichiGAME/collision/continuous/__init__.py
TaichiGAME/collision/continuous/ccd.py
TaichiGAME/common/__init__.py
TaichiGAME/common/camera.py
TaichiGAME/common/config.py
TaichiGAME/common/export_manager.py
TaichiGAME/common/random.py
TaichiGAME/common/ti_viewport.py
TaichiGAME/dynamics/__init__.py
TaichiGAME/dynamics/body.py
TaichiGAME/dynamics/phy_world.py
TaichiGAME/dynamics/ti_phy_world.py
TaichiGAME/dynamics/constraint/__init__.py
TaichiGAME/dynamics/constraint/contact.py
TaichiGAME/dynamics/joint/__init__.py
TaichiGAME/dynamics/joint/distance.py
TaichiGAME/dynamics/joint/joint.py
TaichiGAME/dynamics/joint/point.py
TaichiGAME/dynamics/joint/pulley.py
TaichiGAME/dynamics/joint/revolute.py
TaichiGAME/dynamics/joint/rotation.py
TaichiGAME/examples/__init__.py
TaichiGAME/examples/ggui_demo.py
TaichiGAME/examples/testbed.py
TaichiGAME/examples/ti_testbed.py
TaichiGAME/geometry/__init__.py
TaichiGAME/geometry/geom_algo.py
TaichiGAME/geometry/shape.py
TaichiGAME/math/__init__.py
TaichiGAME/math/base_math.py
TaichiGAME/math/matrix.py
TaichiGAME/planning/__init__.py
TaichiGAME/render/__init__.py
TaichiGAME/render/render.py
TaichiGAME-0.0.3.dist-info/LICENSE
TaichiGAME-0.0.3.dist-info/METADATA
TaichiGAME-0.0.3.dist-info/WHEEL
TaichiGAME-0.0.3.dist-info/top_level.txt
TaichiGAME-0.0.3.dist-info/RECORD
