Metadata-Version: 2.1
Name: TaichiGAME
Version: 0.0.3
Summary: GPU Accelerated Motion Engine based on Taichi Lang
Home-page: https://github.com/maksyuki/TaichiGAME
Author: maksyuki
Author-email: maksyuki@126.com
License: MIT
Project-URL: Documentation, https://github.com/maksyuki/TaichiGAME
Project-URL: Funding, https://donate.pypi.org
Project-URL: Say Thanks!, http://saythanks.io/to/example
Project-URL: Source, https://github.com/maksyuki/TaichiGAME
Project-URL: Tracker, https://github.com/maksyuki/TaichiGAME/issues
Keywords: phyics engine,dynamics simulation,robot motion control
Platform: UNKNOWN
Classifier: Development Status :: 2 - Pre-Alpha
Classifier: License :: OSI Approved :: MIT License
Classifier: Operating System :: POSIX
Classifier: Operating System :: MacOS :: MacOS X
Classifier: Operating System :: Microsoft :: Windows
Classifier: Programming Language :: Python :: 3.7
Classifier: Programming Language :: Python :: 3.8
Classifier: Programming Language :: Python :: 3.9
Classifier: Intended Audience :: Science/Research
Classifier: Intended Audience :: Developers
Classifier: Framework :: Robot Framework :: Library
Classifier: Topic :: Games/Entertainment :: Simulation
Classifier: Topic :: Multimedia :: Graphics
Classifier: Topic :: Scientific/Engineering :: Physics
Classifier: Topic :: Scientific/Engineering :: Visualization
Classifier: Topic :: Software Development :: Libraries :: Application Frameworks
Requires-Python: >=3.7,<3.10
License-File: LICENSE
Requires-Dist: taichi
